replicator/AbstractReplicator.py
replicator/Reformulations.py
replicator/__init__.py
replicator/Shuttering/Shuttering.py
replicator/Shuttering/__init__.py
replicator/Shuttering/_check_inputs.py
replicator/Shuttering/_get_shuttering_id.py
replicator/Shuttering/_import_precomputed_shards.py
replicator/Shuttering/_random_sharding.py
replicator/Shuttering/build_shards.py
replicator/Shuttering/evaluate.py
replicator/Shuttering/get_replicates.py
replicator/Shuttering/shuttering_utils.py
retrieval/__init__.py
retrieval/indexing.py
retrieval/pipeline_factory.py
retrieval/pyterrier2trec.py
retrieval/retrieving.py
retrieval/models/__init__.py
trecdata/TrecCollection.py
trecdata/__init__.py
utils/Logger.py
utils/__init__.py
utils/utils.py
pyreus-0.0.3.dist-info/LICENCE
pyreus-0.0.3.dist-info/METADATA
pyreus-0.0.3.dist-info/WHEEL
pyreus-0.0.3.dist-info/top_level.txt
pyreus-0.0.3.dist-info/RECORD
