Metadata-Version: 2.1
Name: pyreus
Version: 0.0.3
Summary: pyReus a PYthon information REtrieval Utility Services package
Home-page: https://github.com/pypa/sampleproject
Author: Guglielmo Faggioli
Author-email: guglielmo.faggioli@phd.unipd.it
License: UNKNOWN
Project-URL: Bug Tracker, https://github.com/pypa/sampleproject/issues
Platform: UNKNOWN
Classifier: Programming Language :: Python :: 3
Classifier: License :: OSI Approved :: MIT License
Classifier: Operating System :: OS Independent
Requires-Python: >=3.8
License-File: LICENCE
